Blazeio/__init__.py
Blazeio/__main__.py
Blazeio/Client/__init__.py
Blazeio/Client/__main__.py
Blazeio/Client/other.py
Blazeio/Client/protocol.py
Blazeio/Client/test.py
Blazeio/Client/tools.py
Blazeio/Client/__pycache__/__init__.cpython-311.pyc
Blazeio/Client/__pycache__/__init__.cpython-312.pyc
Blazeio/Client/__pycache__/__init__.cpython-313.pyc
Blazeio/Client/__pycache__/__main__.cpython-312.pyc
Blazeio/Client/__pycache__/protocol.cpython-311.pyc
Blazeio/Client/__pycache__/protocol.cpython-312.pyc
Blazeio/Client/__pycache__/test.cpython-312.pyc
Blazeio/Client/__pycache__/tools.cpython-311.pyc
Blazeio/Client/__pycache__/tools.cpython-312.pyc
Blazeio/Dependencies/__init__.py
Blazeio/Dependencies/alts.py
Blazeio/Extensions/Blazeio_iourllib.c
Blazeio/Extensions/__init__.py
Blazeio/Extensions/c_request_util.c
Blazeio/Extensions/client_payload_gen.c
Blazeio/Extensions/setup_build.py
Blazeio/Extensions/simple_serve_util.c
Blazeio/Modules/IN_MEMORY_STATIC_CACHE.py
Blazeio/Modules/__init__.py
Blazeio/Modules/extratools.py
Blazeio/Modules/onrender.py
Blazeio/Modules/protocol.py
Blazeio/Modules/reasons.py
Blazeio/Modules/request.py
Blazeio/Modules/safeguards.py
Blazeio/Modules/server_tools.py
Blazeio/Modules/static.py
Blazeio/Modules/streaming.py
Blazeio/Modules/templatify.py
Blazeio/Other/__init__.py
Blazeio/Other/_refuture.py
Blazeio/Other/algorithms.py
Blazeio/Other/__pycache__/__init__.cpython-312.pyc
Blazeio/Other/__pycache__/algorithms.cpython-312.pyc
Blazeio-2.1.4.6.dist-info/LICENSE
Blazeio-2.1.4.6.dist-info/METADATA
Blazeio-2.1.4.6.dist-info/WHEEL
Blazeio-2.1.4.6.dist-info/entry_points.txt
Blazeio-2.1.4.6.dist-info/top_level.txt
Blazeio-2.1.4.6.dist-info/RECORD
