Metadata-Version: 2.1
Name: Blazeio
Version: 2.1.4.6
Summary: Blazeio
Home-page: https://github.com/anonyxbiz/Blazeio
Author: Anonyxbiz
Author-email: anonyxbiz@gmail.com
License: MIT
Classifier: Programming Language :: Python :: 3
Classifier: Programming Language :: C
Classifier: License :: OSI Approved :: MIT License
Classifier: Operating System :: OS Independent
Requires-Python: >=3.6
License-File: LICENSE
Requires-Dist: ujson
Requires-Dist: aiofile
Requires-Dist: brotlicffi
Requires-Dist: psutil
